psyhub/__init__.py
psyhub-0.0.0a0.dist-info/METADATA
psyhub-0.0.0a0.dist-info/WHEEL
psyhub-0.0.0a0.dist-info/top_level.txt
psyhub-0.0.0a0.dist-info/RECORD
