Metadata-Version: 2.4
Name: psyhub
Version: 0.0.0a0
Summary: The Python client for the PsyHub API.
Requires-Python: >=3.11
